shinyswatch/__init__.py
shinyswatch/_assert.py
shinyswatch/_bsw5.py
shinyswatch/_get_theme.py
shinyswatch/_theme_deps.py
shinyswatch/_theme_picker.py
shinyswatch/_theme_shinyswatch.py
shinyswatch/_typing_extensions.py
shinyswatch/py.typed
shinyswatch/theme.py
shinyswatch/bsw5/cerulean/bootswatch.min.css
shinyswatch/bsw5/cosmo/bootswatch.min.css
shinyswatch/bsw5/cyborg/bootswatch.min.css
shinyswatch/bsw5/darkly/bootswatch.min.css
shinyswatch/bsw5/flatly/bootswatch.min.css
shinyswatch/bsw5/journal/bootswatch.min.css
shinyswatch/bsw5/litera/bootswatch.min.css
shinyswatch/bsw5/lumen/bootswatch.min.css
shinyswatch/bsw5/lux/bootswatch.min.css
shinyswatch/bsw5/materia/bootswatch.min.css
shinyswatch/bsw5/minty/bootswatch.min.css
shinyswatch/bsw5/morph/bootswatch.min.css
shinyswatch/bsw5/pulse/bootswatch.min.css
shinyswatch/bsw5/quartz/bootswatch.min.css
shinyswatch/bsw5/sandstone/bootswatch.min.css
shinyswatch/bsw5/simplex/bootswatch.min.css
shinyswatch/bsw5/sketchy/bootswatch.min.css
shinyswatch/bsw5/slate/bootswatch.min.css
shinyswatch/bsw5/solar/bootswatch.min.css
shinyswatch/bsw5/spacelab/bootswatch.min.css
shinyswatch/bsw5/superhero/bootswatch.min.css
shinyswatch/bsw5/united/bootswatch.min.css
shinyswatch/bsw5/vapor/bootswatch.min.css
shinyswatch/bsw5/yeti/bootswatch.min.css
shinyswatch/bsw5/zephyr/bootswatch.min.css
shinyswatch/picker/theme_picker.css
shinyswatch/picker/theme_picker.js
shinyswatch-0.8.0.dist-info/LICENSE
shinyswatch-0.8.0.dist-info/METADATA
shinyswatch-0.8.0.dist-info/WHEEL
shinyswatch-0.8.0.dist-info/top_level.txt
shinyswatch-0.8.0.dist-info/RECORD
