Metadata-Version: 2.1
Name: shinyswatch
Version: 0.8.0
Summary: Bootswatch + Bootstrap 5 themes for Shiny.
Home-page: https://github.com/rstudio/py-shinyswatch
Author: Barret Schloerke
Author-email: barret@posit.co
Project-URL: Bug Tracker, https://github.com/rstudio/py-shinyswatch/issues
Project-URL: Source Code, https://github.com/rstudio/py-shinyswatch
Keywords: html
Platform: any
Classifier: Development Status :: 2 - Pre-Alpha
Classifier: Intended Audience :: Developers
Classifier: License :: OSI Approved :: MIT License
Classifier: Programming Language :: Python
Classifier: Programming Language :: Python :: 3.9
Classifier: Programming Language :: Python :: 3.10
Classifier: Programming Language :: Python :: 3.11
Classifier: Programming Language :: Python :: 3.12
Classifier: Programming Language :: Python :: 3.13
Classifier: Programming Language :: Python :: Implementation :: PyPy
Classifier: Topic :: Internet :: WWW/HTTP :: Dynamic Content
Classifier: Topic :: Software Development :: Libraries :: Python Modules
Classifier: Topic :: Text Processing :: Markup :: HTML
Requires-Python: >=3.8
License-File: LICENSE
Requires-Dist: typing-extensions>=3.10.0.0
Requires-Dist: packaging>=20.9
Requires-Dist: htmltools>=0.2.0
Requires-Dist: shiny>=1.2.0
Provides-Extra: test
Requires-Dist: pytest>=6.2.4; extra == "test"
Provides-Extra: dev
Requires-Dist: black>=23.1.0; extra == "dev"
Requires-Dist: flake8>=6.0.0; extra == "dev"
Requires-Dist: isort>=5.11.2; extra == "dev"
Requires-Dist: pyright>=1.1.301; extra == "dev"
Requires-Dist: pre-commit>=2.15.0; extra == "dev"
Requires-Dist: wheel; extra == "dev"
Requires-Dist: pandas; extra == "dev"
Requires-Dist: Jinja2; extra == "dev"
Requires-Dist: matplotlib; extra == "dev"
Requires-Dist: libsass; extra == "dev"
Requires-Dist: tinycss2; extra == "dev"
Provides-Extra: docs
Requires-Dist: griffe==0.47.0; extra == "docs"
Requires-Dist: quartodoc==0.7.5; extra == "docs"
Requires-Dist: shinylive; extra == "docs"
Requires-Dist: plum-dispatch; extra == "docs"
Requires-Dist: jupyter; extra == "docs"
